GasolinaMexicoExtractor/__init__.py
GasolinaMexicoExtractor/extractor.py
GasolinaMexicoExtractor-0.1.0.dist-info/LICENSE
GasolinaMexicoExtractor-0.1.0.dist-info/METADATA
GasolinaMexicoExtractor-0.1.0.dist-info/WHEEL
GasolinaMexicoExtractor-0.1.0.dist-info/top_level.txt
GasolinaMexicoExtractor-0.1.0.dist-info/RECORD
